{
  "slug": "Kat",
  "name": "Kat",
  "version": "1.0.0",
  "license": "proprietary",
  "brand": "Kat",
  "author": "",
  "authorEmail": "",
  "authorUrl": "",
  "pluginUrl": "",
  "manualUrl": "",
  "sourceUrl": "",
  "donateUrl": "",
  "changelogUrl": "",
  "modules": [
    {
      "slug": "Shh",
      "name": "Shh",
      "description": "",
      "tags": []
    },
    {
      "slug": "MidiReader",
      "name": "MidiReader",
      "description": "Reads midi from file, outputs CV and Gate",
      "tags": [
        "midi"
      ]
    },
    {
      "slug": "Labeler",
      "name": "Labeler",
      "description": "",
      "tags": []
    }
  ]
}